mongoladdu/__init__.py
mongoladdu/cli.py
mongoladdu/logger.py
mongoladdu/migrations.py
mongoladdu-0.0.1.dist-info/METADATA
mongoladdu-0.0.1.dist-info/RECORD
mongoladdu-0.0.1.dist-info/WHEEL
mongoladdu-0.0.1.dist-info/entry_points.txt
mongoladdu-0.0.1.dist-info/top_level.txt
